{
    "input_path": "/kaggle/input/datasets/amasikifthakerhamim/images/images/image_004.jpg",
    "page_index": null,
    "model_settings": {
        "use_doc_preprocessor": false,
        "use_textline_orientation": false
    },
    "dt_polys": [
        [
            [
                71,
                105
            ],
            [
                371,
                105
            ],
            [
                371,
                118
            ],
            [
                71,
                118
            ]
        ],
        [
            [
                156,
                133
            ],
            [
                448,
                133
            ],
            [
                448,
                146
            ],
            [
                156,
                146
            ]
        ],
        [
            [
                247,
                145
            ],
            [
                358,
                145
            ],
            [
                358,
                158
            ],
            [
                247,
                158
            ]
        ],
        [
            [
                58,
                167
            ],
            [
                103,
                167
            ],
            [
                103,
                182
            ],
            [
                58,
                182
            ]
        ],
        [
            [
                58,
                192
            ],
            [
                149,
                192
            ],
            [
                149,
                206
            ],
            [
                58,
                206
            ]
        ],
        [
            [
                58,
                216
            ],
            [
                537,
                216
            ],
            [
                537,
                230
            ],
            [
                58,
                230
            ]
        ],
        [
            [
                132,
                229
            ],
            [
                179,
                229
            ],
            [
                179,
                240
            ],
            [
                132,
                240
            ]
        ],
        [
            [
                58,
                251
            ],
            [
                273,
                252
            ],
            [
                273,
                266
            ],
            [
                58,
                265
            ]
        ],
        [
            [
                131,
                265
            ],
            [
                178,
                265
            ],
            [
                178,
                276
            ],
            [
                131,
                276
            ]
        ],
        [
            [
                57,
                285
            ],
            [
                450,
                287
            ],
            [
                450,
                301
            ],
            [
                57,
                299
            ]
        ],
        [
            [
                130,
                299
            ],
            [
                233,
                299
            ],
            [
                233,
                311
            ],
            [
                130,
                311
            ]
        ],
        [
            [
                58,
                320
            ],
            [
                264,
                320
            ],
            [
                264,
                334
            ],
            [
                58,
                334
            ]
        ],
        [
            [
                131,
                334
            ],
            [
                161,
                334
            ],
            [
                161,
                345
            ],
            [
                131,
                345
            ]
        ],
        [
            [
                58,
                355
            ],
            [
                166,
                355
            ],
            [
                166,
                369
            ],
            [
                58,
                369
            ]
        ],
        [
            [
                59,
                381
            ],
            [
                118,
                381
            ],
            [
                118,
                392
            ],
            [
                59,
                392
            ]
        ],
        [
            [
                130,
                380
            ],
            [
                324,
                380
            ],
            [
                324,
                393
            ],
            [
                130,
                393
            ]
        ],
        [
            [
                132,
                392
            ],
            [
                232,
                392
            ],
            [
                232,
                405
            ],
            [
                132,
                405
            ]
        ],
        [
            [
                129,
                416
            ],
            [
                198,
                416
            ],
            [
                198,
                426
            ],
            [
                129,
                426
            ]
        ],
        [
            [
                150,
                431
            ],
            [
                159,
                431
            ],
            [
                159,
                437
            ],
            [
                150,
                437
            ]
        ],
        [
            [
                166,
                426
            ],
            [
                254,
                426
            ],
            [
                254,
                439
            ],
            [
                166,
                439
            ]
        ],
        [
            [
                148,
                441
            ],
            [
                159,
                441
            ],
            [
                159,
                449
            ],
            [
                148,
                449
            ]
        ],
        [
            [
                165,
                438
            ],
            [
                266,
                438
            ],
            [
                266,
                451
            ],
            [
                165,
                451
            ]
        ],
        [
            [
                148,
                453
            ],
            [
                160,
                453
            ],
            [
                160,
                461
            ],
            [
                148,
                461
            ]
        ],
        [
            [
                166,
                450
            ],
            [
                303,
                450
            ],
            [
                303,
                463
            ],
            [
                166,
                463
            ]
        ],
        [
            [
                164,
                462
            ],
            [
                245,
                462
            ],
            [
                245,
                475
            ],
            [
                164,
                475
            ]
        ],
        [
            [
                130,
                473
            ],
            [
                231,
                473
            ],
            [
                231,
                486
            ],
            [
                130,
                486
            ]
        ],
        [
            [
                147,
                488
            ],
            [
                167,
                488
            ],
            [
                167,
                496
            ],
            [
                147,
                496
            ]
        ],
        [
            [
                163,
                485
            ],
            [
                288,
                485
            ],
            [
                288,
                498
            ],
            [
                163,
                498
            ]
        ],
        [
            [
                59,
                508
            ],
            [
                137,
                508
            ],
            [
                137,
                522
            ],
            [
                59,
                522
            ]
        ],
        [
            [
                56,
                528
            ],
            [
                233,
                529
            ],
            [
                233,
                546
            ],
            [
                56,
                544
            ]
        ],
        [
            [
                57,
                551
            ],
            [
                295,
                553
            ],
            [
                295,
                570
            ],
            [
                57,
                568
            ]
        ],
        [
            [
                132,
                564
            ],
            [
                161,
                567
            ],
            [
                160,
                581
            ],
            [
                131,
                578
            ]
        ],
        [
            [
                58,
                590
            ],
            [
                166,
                590
            ],
            [
                166,
                603
            ],
            [
                58,
                603
            ]
        ],
        [
            [
                59,
                614
            ],
            [
                119,
                614
            ],
            [
                119,
                625
            ],
            [
                59,
                625
            ]
        ],
        [
            [
                127,
                612
            ],
            [
                265,
                613
            ],
            [
                265,
                627
            ],
            [
                127,
                626
            ]
        ],
        [
            [
                130,
                625
            ],
            [
                363,
                624
            ],
            [
                363,
                638
            ],
            [
                130,
                639
            ]
        ]
    ],
    "text_det_params": {
        "limit_side_len": 64,
        "limit_type": "min",
        "thresh": 0.3,
        "max_side_limit": 4000,
        "box_thresh": 0.6,
        "unclip_ratio": 1.5
    },
    "text_type": "general",
    "textline_orientation_angles": [
        -1,
        -1,
        -1,
        -1,
        -1,
        -1,
        -1,
        -1,
        -1,
        -1,
        -1,
        -1,
        -1,
        -1,
        -1,
        -1,
        -1,
        -1,
        -1,
        -1,
        -1,
        -1,
        -1,
        -1,
        -1,
        -1,
        -1,
        -1,
        -1,
        -1,
        -1,
        -1,
        -1,
        -1,
        -1,
        -1
    ],
    "text_rec_score_thresh": 0.0,
    "return_word_box": false,
    "rec_texts": [
        "PROFESSIONAL DEVELOPMENT AGENDA",
        "Teacher Orientation and Professional Development",
        "August 19- 21, 2009",
        "Agenda",
        "Wednesday, 8/19",
        "9:00 - 10:00 Welcome; overview of whole school initiatives for the year. (Rooms 107 and 108)",
        "Principal",
        "10:00- 10:30 Whole school team building",
        "Principal",
        "10:30 - 11:00 Connection between The Leaming Project and RCS; technology",
        "Karen and Principal",
        "11:00 - 12:00 New employee paperwork",
        "Kerin",
        "12:00 -1:00 Lunch",
        "1:00-4:00",
        "Curriculum and instruction workshops",
        "Christine and Chad",
        "Whole school",
        "o",
        "Long tem plans",
        "o",
        "Lesson plan fom at",
        "0",
        "Monthly parent newsletter",
        "Team planning",
        "Grade-level teams",
        "o",
        "Pa rent/student syllabus",
        "Thursday, 8/20",
        "8:00 - 8:30 Work time in rooms",
        "8:30 -12:30 Literacy training (whole school)",
        "Gaby",
        "12:30- 1:30 Lunch",
        "1:30-3:00",
        "Advisory/Morning meeting",
        "Christine, Chad, Allie, Ray, Omalara, Roshone"
    ],
    "rec_scores": [
        0.9907823801040649,
        0.9940971732139587,
        0.9749680757522583,
        0.9998572468757629,
        0.9569607377052307,
        0.9711346626281738,
        0.9897968769073486,
        0.971997082233429,
        0.9672727584838867,
        0.9811903834342957,
        0.9772950410842896,
        0.9745292663574219,
        0.9973003268241882,
        0.9478378295898438,
        0.9995276927947998,
        0.9992125630378723,
        0.9712222218513489,
        0.992651641368866,
        0.5146868228912354,
        0.9973066449165344,
        0.7439867854118347,
        0.9796217679977417,
        0.5043830871582031,
        0.9919062852859497,
        0.9984344244003296,
        0.9899863004684448,
        0.6198761463165283,
        0.9857767224311829,
        0.9527354836463928,
        0.9546446204185486,
        0.9687020778656006,
        0.9994649887084961,
        0.9548922181129456,
        0.9987921118736267,
        0.9827566742897034,
        0.9781634211540222
    ],
    "rec_polys": [
        [
            [
                71,
                105
            ],
            [
                371,
                105
            ],
            [
                371,
                118
            ],
            [
                71,
                118
            ]
        ],
        [
            [
                156,
                133
            ],
            [
                448,
                133
            ],
            [
                448,
                146
            ],
            [
                156,
                146
            ]
        ],
        [
            [
                247,
                145
            ],
            [
                358,
                145
            ],
            [
                358,
                158
            ],
            [
                247,
                158
            ]
        ],
        [
            [
                58,
                167
            ],
            [
                103,
                167
            ],
            [
                103,
                182
            ],
            [
                58,
                182
            ]
        ],
        [
            [
                58,
                192
            ],
            [
                149,
                192
            ],
            [
                149,
                206
            ],
            [
                58,
                206
            ]
        ],
        [
            [
                58,
                216
            ],
            [
                537,
                216
            ],
            [
                537,
                230
            ],
            [
                58,
                230
            ]
        ],
        [
            [
                132,
                229
            ],
            [
                179,
                229
            ],
            [
                179,
                240
            ],
            [
                132,
                240
            ]
        ],
        [
            [
                58,
                251
            ],
            [
                273,
                252
            ],
            [
                273,
                266
            ],
            [
                58,
                265
            ]
        ],
        [
            [
                131,
                265
            ],
            [
                178,
                265
            ],
            [
                178,
                276
            ],
            [
                131,
                276
            ]
        ],
        [
            [
                57,
                285
            ],
            [
                450,
                287
            ],
            [
                450,
                301
            ],
            [
                57,
                299
            ]
        ],
        [
            [
                130,
                299
            ],
            [
                233,
                299
            ],
            [
                233,
                311
            ],
            [
                130,
                311
            ]
        ],
        [
            [
                58,
                320
            ],
            [
                264,
                320
            ],
            [
                264,
                334
            ],
            [
                58,
                334
            ]
        ],
        [
            [
                131,
                334
            ],
            [
                161,
                334
            ],
            [
                161,
                345
            ],
            [
                131,
                345
            ]
        ],
        [
            [
                58,
                355
            ],
            [
                166,
                355
            ],
            [
                166,
                369
            ],
            [
                58,
                369
            ]
        ],
        [
            [
                59,
                381
            ],
            [
                118,
                381
            ],
            [
                118,
                392
            ],
            [
                59,
                392
            ]
        ],
        [
            [
                130,
                380
            ],
            [
                324,
                380
            ],
            [
                324,
                393
            ],
            [
                130,
                393
            ]
        ],
        [
            [
                132,
                392
            ],
            [
                232,
                392
            ],
            [
                232,
                405
            ],
            [
                132,
                405
            ]
        ],
        [
            [
                129,
                416
            ],
            [
                198,
                416
            ],
            [
                198,
                426
            ],
            [
                129,
                426
            ]
        ],
        [
            [
                150,
                431
            ],
            [
                159,
                431
            ],
            [
                159,
                437
            ],
            [
                150,
                437
            ]
        ],
        [
            [
                166,
                426
            ],
            [
                254,
                426
            ],
            [
                254,
                439
            ],
            [
                166,
                439
            ]
        ],
        [
            [
                148,
                441
            ],
            [
                159,
                441
            ],
            [
                159,
                449
            ],
            [
                148,
                449
            ]
        ],
        [
            [
                165,
                438
            ],
            [
                266,
                438
            ],
            [
                266,
                451
            ],
            [
                165,
                451
            ]
        ],
        [
            [
                148,
                453
            ],
            [
                160,
                453
            ],
            [
                160,
                461
            ],
            [
                148,
                461
            ]
        ],
        [
            [
                166,
                450
            ],
            [
                303,
                450
            ],
            [
                303,
                463
            ],
            [
                166,
                463
            ]
        ],
        [
            [
                164,
                462
            ],
            [
                245,
                462
            ],
            [
                245,
                475
            ],
            [
                164,
                475
            ]
        ],
        [
            [
                130,
                473
            ],
            [
                231,
                473
            ],
            [
                231,
                486
            ],
            [
                130,
                486
            ]
        ],
        [
            [
                147,
                488
            ],
            [
                167,
                488
            ],
            [
                167,
                496
            ],
            [
                147,
                496
            ]
        ],
        [
            [
                163,
                485
            ],
            [
                288,
                485
            ],
            [
                288,
                498
            ],
            [
                163,
                498
            ]
        ],
        [
            [
                59,
                508
            ],
            [
                137,
                508
            ],
            [
                137,
                522
            ],
            [
                59,
                522
            ]
        ],
        [
            [
                56,
                528
            ],
            [
                233,
                529
            ],
            [
                233,
                546
            ],
            [
                56,
                544
            ]
        ],
        [
            [
                57,
                551
            ],
            [
                295,
                553
            ],
            [
                295,
                570
            ],
            [
                57,
                568
            ]
        ],
        [
            [
                132,
                564
            ],
            [
                161,
                567
            ],
            [
                160,
                581
            ],
            [
                131,
                578
            ]
        ],
        [
            [
                58,
                590
            ],
            [
                166,
                590
            ],
            [
                166,
                603
            ],
            [
                58,
                603
            ]
        ],
        [
            [
                59,
                614
            ],
            [
                119,
                614
            ],
            [
                119,
                625
            ],
            [
                59,
                625
            ]
        ],
        [
            [
                127,
                612
            ],
            [
                265,
                613
            ],
            [
                265,
                627
            ],
            [
                127,
                626
            ]
        ],
        [
            [
                130,
                625
            ],
            [
                363,
                624
            ],
            [
                363,
                638
            ],
            [
                130,
                639
            ]
        ]
    ],
    "rec_boxes": [
        [
            71,
            105,
            371,
            118
        ],
        [
            156,
            133,
            448,
            146
        ],
        [
            247,
            145,
            358,
            158
        ],
        [
            58,
            167,
            103,
            182
        ],
        [
            58,
            192,
            149,
            206
        ],
        [
            58,
            216,
            537,
            230
        ],
        [
            132,
            229,
            179,
            240
        ],
        [
            58,
            251,
            273,
            266
        ],
        [
            131,
            265,
            178,
            276
        ],
        [
            57,
            285,
            450,
            301
        ],
        [
            130,
            299,
            233,
            311
        ],
        [
            58,
            320,
            264,
            334
        ],
        [
            131,
            334,
            161,
            345
        ],
        [
            58,
            355,
            166,
            369
        ],
        [
            59,
            381,
            118,
            392
        ],
        [
            130,
            380,
            324,
            393
        ],
        [
            132,
            392,
            232,
            405
        ],
        [
            129,
            416,
            198,
            426
        ],
        [
            150,
            431,
            159,
            437
        ],
        [
            166,
            426,
            254,
            439
        ],
        [
            148,
            441,
            159,
            449
        ],
        [
            165,
            438,
            266,
            451
        ],
        [
            148,
            453,
            160,
            461
        ],
        [
            166,
            450,
            303,
            463
        ],
        [
            164,
            462,
            245,
            475
        ],
        [
            130,
            473,
            231,
            486
        ],
        [
            147,
            488,
            167,
            496
        ],
        [
            163,
            485,
            288,
            498
        ],
        [
            59,
            508,
            137,
            522
        ],
        [
            56,
            528,
            233,
            546
        ],
        [
            57,
            551,
            295,
            570
        ],
        [
            131,
            564,
            161,
            581
        ],
        [
            58,
            590,
            166,
            603
        ],
        [
            59,
            614,
            119,
            625
        ],
        [
            127,
            612,
            265,
            627
        ],
        [
            130,
            624,
            363,
            639
        ]
    ]
}