{
    "input_path": "/kaggle/input/datasets/amasikifthakerhamim/test-dataset-100/test_dataset_100/form_18.jpg",
    "page_index": null,
    "model_settings": {
        "use_doc_preprocessor": false,
        "use_textline_orientation": false
    },
    "dt_polys": [
        [
            [
                359,
                67
            ],
            [
                528,
                68
            ],
            [
                528,
                85
            ],
            [
                359,
                84
            ]
        ],
        [
            [
                190,
                137
            ],
            [
                406,
                137
            ],
            [
                406,
                158
            ],
            [
                190,
                158
            ]
        ],
        [
            [
                223,
                168
            ],
            [
                373,
                167
            ],
            [
                373,
                198
            ],
            [
                223,
                199
            ]
        ],
        [
            [
                67,
                221
            ],
            [
                228,
                221
            ],
            [
                228,
                234
            ],
            [
                67,
                234
            ]
        ],
        [
            [
                66,
                254
            ],
            [
                126,
                254
            ],
            [
                126,
                268
            ],
            [
                66,
                268
            ]
        ],
        [
            [
                66,
                285
            ],
            [
                137,
                285
            ],
            [
                137,
                302
            ],
            [
                66,
                302
            ]
        ],
        [
            [
                65,
                316
            ],
            [
                125,
                316
            ],
            [
                125,
                333
            ],
            [
                65,
                333
            ]
        ],
        [
            [
                66,
                348
            ],
            [
                143,
                348
            ],
            [
                143,
                365
            ],
            [
                66,
                365
            ]
        ],
        [
            [
                67,
                380
            ],
            [
                175,
                380
            ],
            [
                175,
                397
            ],
            [
                67,
                397
            ]
        ],
        [
            [
                67,
                415
            ],
            [
                152,
                415
            ],
            [
                152,
                428
            ],
            [
                67,
                428
            ]
        ],
        [
            [
                65,
                444
            ],
            [
                107,
                444
            ],
            [
                107,
                463
            ],
            [
                65,
                463
            ]
        ],
        [
            [
                68,
                477
            ],
            [
                372,
                477
            ],
            [
                372,
                494
            ],
            [
                68,
                494
            ]
        ],
        [
            [
                67,
                511
            ],
            [
                482,
                511
            ],
            [
                482,
                525
            ],
            [
                67,
                525
            ]
        ],
        [
            [
                68,
                542
            ],
            [
                482,
                542
            ],
            [
                482,
                555
            ],
            [
                68,
                555
            ]
        ],
        [
            [
                65,
                573
            ],
            [
                146,
                573
            ],
            [
                146,
                591
            ],
            [
                65,
                591
            ]
        ],
        [
            [
                65,
                606
            ],
            [
                176,
                606
            ],
            [
                176,
                623
            ],
            [
                65,
                623
            ]
        ]
    ],
    "text_det_params": {
        "limit_side_len": 64,
        "limit_type": "min",
        "thresh": 0.3,
        "max_side_limit": 4000,
        "box_thresh": 0.6,
        "unclip_ratio": 1.5
    },
    "text_type": "general",
    "textline_orientation_angles": [
        -1,
        -1,
        -1,
        -1,
        -1,
        -1,
        -1,
        -1,
        -1,
        -1,
        -1,
        -1,
        -1,
        -1,
        -1,
        -1
    ],
    "text_rec_score_thresh": 0.0,
    "return_word_box": false,
    "rec_texts": [
        "GOAL: Fill Out A Job Application",
        "JOB APPLICATION",
        "SAMPLE",
        "PERSONALINFORMATION:",
        "First Name",
        "Middle Name",
        "Last Name",
        "Street Address",
        "City, State, Zip Code",
        "Phone Number (",
        "E-mail",
        "Are you eligible to work in the United States? YesNo",
        "If you are under age 18, do you have an employment/age certificate? YesNo",
        "Have you been convicted of or pleaded no contest to a felony within the last five years?",
        "YesNo",
        "If yes, please explain:"
    ],
    "rec_scores": [
        0.9914020299911499,
        0.9846480488777161,
        0.9999189376831055,
        0.9999114274978638,
        0.9998782873153687,
        0.9686518311500549,
        0.9688794612884521,
        0.9996566772460938,
        0.9991936683654785,
        0.9848284125328064,
        0.9994598031044006,
        0.9881306290626526,
        0.9866769909858704,
        0.9933862090110779,
        0.995724081993103,
        0.9979811310768127
    ],
    "rec_polys": [
        [
            [
                359,
                67
            ],
            [
                528,
                68
            ],
            [
                528,
                85
            ],
            [
                359,
                84
            ]
        ],
        [
            [
                190,
                137
            ],
            [
                406,
                137
            ],
            [
                406,
                158
            ],
            [
                190,
                158
            ]
        ],
        [
            [
                223,
                168
            ],
            [
                373,
                167
            ],
            [
                373,
                198
            ],
            [
                223,
                199
            ]
        ],
        [
            [
                67,
                221
            ],
            [
                228,
                221
            ],
            [
                228,
                234
            ],
            [
                67,
                234
            ]
        ],
        [
            [
                66,
                254
            ],
            [
                126,
                254
            ],
            [
                126,
                268
            ],
            [
                66,
                268
            ]
        ],
        [
            [
                66,
                285
            ],
            [
                137,
                285
            ],
            [
                137,
                302
            ],
            [
                66,
                302
            ]
        ],
        [
            [
                65,
                316
            ],
            [
                125,
                316
            ],
            [
                125,
                333
            ],
            [
                65,
                333
            ]
        ],
        [
            [
                66,
                348
            ],
            [
                143,
                348
            ],
            [
                143,
                365
            ],
            [
                66,
                365
            ]
        ],
        [
            [
                67,
                380
            ],
            [
                175,
                380
            ],
            [
                175,
                397
            ],
            [
                67,
                397
            ]
        ],
        [
            [
                67,
                415
            ],
            [
                152,
                415
            ],
            [
                152,
                428
            ],
            [
                67,
                428
            ]
        ],
        [
            [
                65,
                444
            ],
            [
                107,
                444
            ],
            [
                107,
                463
            ],
            [
                65,
                463
            ]
        ],
        [
            [
                68,
                477
            ],
            [
                372,
                477
            ],
            [
                372,
                494
            ],
            [
                68,
                494
            ]
        ],
        [
            [
                67,
                511
            ],
            [
                482,
                511
            ],
            [
                482,
                525
            ],
            [
                67,
                525
            ]
        ],
        [
            [
                68,
                542
            ],
            [
                482,
                542
            ],
            [
                482,
                555
            ],
            [
                68,
                555
            ]
        ],
        [
            [
                65,
                573
            ],
            [
                146,
                573
            ],
            [
                146,
                591
            ],
            [
                65,
                591
            ]
        ],
        [
            [
                65,
                606
            ],
            [
                176,
                606
            ],
            [
                176,
                623
            ],
            [
                65,
                623
            ]
        ]
    ],
    "rec_boxes": [
        [
            359,
            67,
            528,
            85
        ],
        [
            190,
            137,
            406,
            158
        ],
        [
            223,
            167,
            373,
            199
        ],
        [
            67,
            221,
            228,
            234
        ],
        [
            66,
            254,
            126,
            268
        ],
        [
            66,
            285,
            137,
            302
        ],
        [
            65,
            316,
            125,
            333
        ],
        [
            66,
            348,
            143,
            365
        ],
        [
            67,
            380,
            175,
            397
        ],
        [
            67,
            415,
            152,
            428
        ],
        [
            65,
            444,
            107,
            463
        ],
        [
            68,
            477,
            372,
            494
        ],
        [
            67,
            511,
            482,
            525
        ],
        [
            68,
            542,
            482,
            555
        ],
        [
            65,
            573,
            146,
            591
        ],
        [
            65,
            606,
            176,
            623
        ]
    ]
}