{
    "input_path": "/kaggle/input/datasets/amasikifthakerhamim/test-dataset-100/test_dataset_100/form_19.jpg",
    "page_index": null,
    "model_settings": {
        "use_doc_preprocessor": false,
        "use_textline_orientation": false
    },
    "dt_polys": [
        [
            [
                519,
                81
            ],
            [
                721,
                81
            ],
            [
                721,
                108
            ],
            [
                519,
                108
            ]
        ],
        [
            [
                286,
                105
            ],
            [
                955,
                105
            ],
            [
                955,
                129
            ],
            [
                286,
                129
            ]
        ],
        [
            [
                263,
                144
            ],
            [
                966,
                144
            ],
            [
                966,
                240
            ],
            [
                263,
                240
            ]
        ],
        [
            [
                918,
                265
            ],
            [
                972,
                265
            ],
            [
                972,
                296
            ],
            [
                918,
                296
            ]
        ],
        [
            [
                424,
                392
            ],
            [
                774,
                390
            ],
            [
                775,
                437
            ],
            [
                425,
                439
            ]
        ],
        [
            [
                289,
                463
            ],
            [
                907,
                464
            ],
            [
                907,
                491
            ],
            [
                289,
                490
            ]
        ],
        [
            [
                133,
                541
            ],
            [
                449,
                541
            ],
            [
                449,
                572
            ],
            [
                133,
                572
            ]
        ],
        [
            [
                130,
                622
            ],
            [
                225,
                620
            ],
            [
                226,
                649
            ],
            [
                131,
                651
            ]
        ],
        [
            [
                136,
                669
            ],
            [
                327,
                669
            ],
            [
                327,
                690
            ],
            [
                136,
                690
            ]
        ],
        [
            [
                149,
                718
            ],
            [
                189,
                718
            ],
            [
                189,
                747
            ],
            [
                149,
                747
            ]
        ],
        [
            [
                349,
                724
            ],
            [
                552,
                724
            ],
            [
                552,
                748
            ],
            [
                349,
                748
            ]
        ],
        [
            [
                720,
                724
            ],
            [
                924,
                724
            ],
            [
                924,
                748
            ],
            [
                720,
                748
            ]
        ],
        [
            [
                132,
                767
            ],
            [
                189,
                767
            ],
            [
                189,
                789
            ],
            [
                132,
                789
            ]
        ],
        [
            [
                328,
                768
            ],
            [
                425,
                768
            ],
            [
                425,
                789
            ],
            [
                328,
                789
            ]
        ],
        [
            [
                700,
                768
            ],
            [
                795,
                768
            ],
            [
                795,
                789
            ],
            [
                700,
                789
            ]
        ],
        [
            [
                134,
                858
            ],
            [
                254,
                858
            ],
            [
                254,
                883
            ],
            [
                134,
                883
            ]
        ],
        [
            [
                136,
                904
            ],
            [
                326,
                904
            ],
            [
                326,
                925
            ],
            [
                136,
                925
            ]
        ],
        [
            [
                153,
                958
            ],
            [
                356,
                958
            ],
            [
                356,
                982
            ],
            [
                153,
                982
            ]
        ],
        [
            [
                133,
                1001
            ],
            [
                266,
                1003
            ],
            [
                265,
                1024
            ],
            [
                133,
                1022
            ]
        ],
        [
            [
                154,
                1066
            ],
            [
                356,
                1066
            ],
            [
                356,
                1090
            ],
            [
                154,
                1090
            ]
        ],
        [
            [
                134,
                1110
            ],
            [
                281,
                1110
            ],
            [
                281,
                1130
            ],
            [
                134,
                1130
            ]
        ],
        [
            [
                153,
                1173
            ],
            [
                357,
                1173
            ],
            [
                357,
                1198
            ],
            [
                153,
                1198
            ]
        ],
        [
            [
                627,
                1174
            ],
            [
                829,
                1174
            ],
            [
                829,
                1199
            ],
            [
                627,
                1199
            ]
        ],
        [
            [
                132,
                1213
            ],
            [
                176,
                1216
            ],
            [
                174,
                1244
            ],
            [
                130,
                1241
            ]
        ],
        [
            [
                605,
                1218
            ],
            [
                656,
                1218
            ],
            [
                656,
                1241
            ],
            [
                605,
                1241
            ]
        ],
        [
            [
                153,
                1282
            ],
            [
                357,
                1282
            ],
            [
                357,
                1306
            ],
            [
                153,
                1306
            ]
        ],
        [
            [
                624,
                1277
            ],
            [
                714,
                1277
            ],
            [
                714,
                1305
            ],
            [
                624,
                1305
            ]
        ],
        [
            [
                133,
                1325
            ],
            [
                273,
                1325
            ],
            [
                273,
                1346
            ],
            [
                133,
                1346
            ]
        ],
        [
            [
                605,
                1325
            ],
            [
                680,
                1325
            ],
            [
                680,
                1350
            ],
            [
                605,
                1350
            ]
        ],
        [
            [
                132,
                1413
            ],
            [
                221,
                1413
            ],
            [
                221,
                1442
            ],
            [
                132,
                1442
            ]
        ],
        [
            [
                137,
                1461
            ],
            [
                327,
                1461
            ],
            [
                327,
                1482
            ],
            [
                137,
                1482
            ]
        ],
        [
            [
                153,
                1514
            ],
            [
                357,
                1517
            ],
            [
                357,
                1542
            ],
            [
                153,
                1539
            ]
        ],
        [
            [
                134,
                1561
            ],
            [
                261,
                1561
            ],
            [
                261,
                1581
            ],
            [
                134,
                1581
            ]
        ],
        [
            [
                132,
                1650
            ],
            [
                326,
                1650
            ],
            [
                326,
                1674
            ],
            [
                132,
                1674
            ]
        ]
    ],
    "text_det_params": {
        "limit_side_len": 64,
        "limit_type": "min",
        "thresh": 0.3,
        "max_side_limit": 4000,
        "box_thresh": 0.6,
        "unclip_ratio": 1.5
    },
    "text_type": "general",
    "textline_orientation_angles": [
        -1,
        -1,
        -1,
        -1,
        -1,
        -1,
        -1,
        -1,
        -1,
        -1,
        -1,
        -1,
        -1,
        -1,
        -1,
        -1,
        -1,
        -1,
        -1,
        -1,
        -1,
        -1,
        -1,
        -1,
        -1,
        -1,
        -1,
        -1,
        -1,
        -1,
        -1,
        -1,
        -1,
        -1
    ],
    "text_rec_score_thresh": 0.0,
    "return_word_box": false,
    "rec_texts": [
        "[Your Company Name]",
        "[Your Company Email] I [Your Company Address] I [Your Company Number]",
        "APPLICATION FORM",
        "III",
        "Application Form",
        "Fill out this form with complete and up-to-date information.",
        "Applicant Information",
        "Name*",
        "Description (Optional)",
        "Mr",
        "Type a placeholder",
        "Type a placeholder",
        "Prefix",
        "First Name",
        "Last Name",
        "Address *",
        "Description (Optional)",
        "Type a placeholder",
        "Street Address",
        "Type a placeholder",
        "Street Address 2",
        "Type a placeholder",
        "Type a placeholder",
        "City",
        "State",
        "Type a placeholder",
        "Select...",
        "Postal/Zip Code",
        "Country",
        "Email *",
        "Description (Optional)",
        "Type a placeholder",
        "Email Address",
        "Phone number *"
    ],
    "rec_scores": [
        0.9999207854270935,
        0.9850904941558838,
        0.9998599290847778,
        0.9238082766532898,
        0.999962329864502,
        0.9908714294433594,
        0.9916664361953735,
        0.9848068952560425,
        0.9802398085594177,
        0.9994252920150757,
        0.9987767338752747,
        0.9810118079185486,
        0.9998858571052551,
        0.9970744848251343,
        0.9999037981033325,
        0.9584569931030273,
        0.9988772869110107,
        0.9828541874885559,
        0.9841551780700684,
        0.9990708231925964,
        0.9943432807922363,
        0.999165952205658,
        0.9975510835647583,
        0.9898113012313843,
        0.9999531507492065,
        0.9837796688079834,
        0.9987648725509644,
        0.9991523027420044,
        0.9999679327011108,
        0.9874124526977539,
        0.9997177124023438,
        0.979975163936615,
        0.9980165958404541,
        0.9955657124519348
    ],
    "rec_polys": [
        [
            [
                519,
                81
            ],
            [
                721,
                81
            ],
            [
                721,
                108
            ],
            [
                519,
                108
            ]
        ],
        [
            [
                286,
                105
            ],
            [
                955,
                105
            ],
            [
                955,
                129
            ],
            [
                286,
                129
            ]
        ],
        [
            [
                263,
                144
            ],
            [
                966,
                144
            ],
            [
                966,
                240
            ],
            [
                263,
                240
            ]
        ],
        [
            [
                918,
                265
            ],
            [
                972,
                265
            ],
            [
                972,
                296
            ],
            [
                918,
                296
            ]
        ],
        [
            [
                424,
                392
            ],
            [
                774,
                390
            ],
            [
                775,
                437
            ],
            [
                425,
                439
            ]
        ],
        [
            [
                289,
                463
            ],
            [
                907,
                464
            ],
            [
                907,
                491
            ],
            [
                289,
                490
            ]
        ],
        [
            [
                133,
                541
            ],
            [
                449,
                541
            ],
            [
                449,
                572
            ],
            [
                133,
                572
            ]
        ],
        [
            [
                130,
                622
            ],
            [
                225,
                620
            ],
            [
                226,
                649
            ],
            [
                131,
                651
            ]
        ],
        [
            [
                136,
                669
            ],
            [
                327,
                669
            ],
            [
                327,
                690
            ],
            [
                136,
                690
            ]
        ],
        [
            [
                149,
                718
            ],
            [
                189,
                718
            ],
            [
                189,
                747
            ],
            [
                149,
                747
            ]
        ],
        [
            [
                349,
                724
            ],
            [
                552,
                724
            ],
            [
                552,
                748
            ],
            [
                349,
                748
            ]
        ],
        [
            [
                720,
                724
            ],
            [
                924,
                724
            ],
            [
                924,
                748
            ],
            [
                720,
                748
            ]
        ],
        [
            [
                132,
                767
            ],
            [
                189,
                767
            ],
            [
                189,
                789
            ],
            [
                132,
                789
            ]
        ],
        [
            [
                328,
                768
            ],
            [
                425,
                768
            ],
            [
                425,
                789
            ],
            [
                328,
                789
            ]
        ],
        [
            [
                700,
                768
            ],
            [
                795,
                768
            ],
            [
                795,
                789
            ],
            [
                700,
                789
            ]
        ],
        [
            [
                134,
                858
            ],
            [
                254,
                858
            ],
            [
                254,
                883
            ],
            [
                134,
                883
            ]
        ],
        [
            [
                136,
                904
            ],
            [
                326,
                904
            ],
            [
                326,
                925
            ],
            [
                136,
                925
            ]
        ],
        [
            [
                153,
                958
            ],
            [
                356,
                958
            ],
            [
                356,
                982
            ],
            [
                153,
                982
            ]
        ],
        [
            [
                133,
                1001
            ],
            [
                266,
                1003
            ],
            [
                265,
                1024
            ],
            [
                133,
                1022
            ]
        ],
        [
            [
                154,
                1066
            ],
            [
                356,
                1066
            ],
            [
                356,
                1090
            ],
            [
                154,
                1090
            ]
        ],
        [
            [
                134,
                1110
            ],
            [
                281,
                1110
            ],
            [
                281,
                1130
            ],
            [
                134,
                1130
            ]
        ],
        [
            [
                153,
                1173
            ],
            [
                357,
                1173
            ],
            [
                357,
                1198
            ],
            [
                153,
                1198
            ]
        ],
        [
            [
                627,
                1174
            ],
            [
                829,
                1174
            ],
            [
                829,
                1199
            ],
            [
                627,
                1199
            ]
        ],
        [
            [
                132,
                1213
            ],
            [
                176,
                1216
            ],
            [
                174,
                1244
            ],
            [
                130,
                1241
            ]
        ],
        [
            [
                605,
                1218
            ],
            [
                656,
                1218
            ],
            [
                656,
                1241
            ],
            [
                605,
                1241
            ]
        ],
        [
            [
                153,
                1282
            ],
            [
                357,
                1282
            ],
            [
                357,
                1306
            ],
            [
                153,
                1306
            ]
        ],
        [
            [
                624,
                1277
            ],
            [
                714,
                1277
            ],
            [
                714,
                1305
            ],
            [
                624,
                1305
            ]
        ],
        [
            [
                133,
                1325
            ],
            [
                273,
                1325
            ],
            [
                273,
                1346
            ],
            [
                133,
                1346
            ]
        ],
        [
            [
                605,
                1325
            ],
            [
                680,
                1325
            ],
            [
                680,
                1350
            ],
            [
                605,
                1350
            ]
        ],
        [
            [
                132,
                1413
            ],
            [
                221,
                1413
            ],
            [
                221,
                1442
            ],
            [
                132,
                1442
            ]
        ],
        [
            [
                137,
                1461
            ],
            [
                327,
                1461
            ],
            [
                327,
                1482
            ],
            [
                137,
                1482
            ]
        ],
        [
            [
                153,
                1514
            ],
            [
                357,
                1517
            ],
            [
                357,
                1542
            ],
            [
                153,
                1539
            ]
        ],
        [
            [
                134,
                1561
            ],
            [
                261,
                1561
            ],
            [
                261,
                1581
            ],
            [
                134,
                1581
            ]
        ],
        [
            [
                132,
                1650
            ],
            [
                326,
                1650
            ],
            [
                326,
                1674
            ],
            [
                132,
                1674
            ]
        ]
    ],
    "rec_boxes": [
        [
            519,
            81,
            721,
            108
        ],
        [
            286,
            105,
            955,
            129
        ],
        [
            263,
            144,
            966,
            240
        ],
        [
            918,
            265,
            972,
            296
        ],
        [
            424,
            390,
            775,
            439
        ],
        [
            289,
            463,
            907,
            491
        ],
        [
            133,
            541,
            449,
            572
        ],
        [
            130,
            620,
            226,
            651
        ],
        [
            136,
            669,
            327,
            690
        ],
        [
            149,
            718,
            189,
            747
        ],
        [
            349,
            724,
            552,
            748
        ],
        [
            720,
            724,
            924,
            748
        ],
        [
            132,
            767,
            189,
            789
        ],
        [
            328,
            768,
            425,
            789
        ],
        [
            700,
            768,
            795,
            789
        ],
        [
            134,
            858,
            254,
            883
        ],
        [
            136,
            904,
            326,
            925
        ],
        [
            153,
            958,
            356,
            982
        ],
        [
            133,
            1001,
            266,
            1024
        ],
        [
            154,
            1066,
            356,
            1090
        ],
        [
            134,
            1110,
            281,
            1130
        ],
        [
            153,
            1173,
            357,
            1198
        ],
        [
            627,
            1174,
            829,
            1199
        ],
        [
            130,
            1213,
            176,
            1244
        ],
        [
            605,
            1218,
            656,
            1241
        ],
        [
            153,
            1282,
            357,
            1306
        ],
        [
            624,
            1277,
            714,
            1305
        ],
        [
            133,
            1325,
            273,
            1346
        ],
        [
            605,
            1325,
            680,
            1350
        ],
        [
            132,
            1413,
            221,
            1442
        ],
        [
            137,
            1461,
            327,
            1482
        ],
        [
            153,
            1514,
            357,
            1542
        ],
        [
            134,
            1561,
            261,
            1581
        ],
        [
            132,
            1650,
            326,
            1674
        ]
    ]
}